{
    "os": "Linux-5.15.133+-x86_64-with-glibc2.31",
    "python": "3.10.13",
    "heartbeatAt": "2024-05-24T02:21:51.176524",
    "startedAt": "2024-05-24T02:21:51.083099",
    "docker": null,
    "cuda": null,
    "args": [
        "-f",
        "/tmp/tmpvz_gru3p.json",
        "--HistoryManager.hist_file=:memory:"
    ],
    "state": "running",
    "program": "<python with no main file>",
    "codePathLocal": null,
    "host": "65e462eb19db",
    "username": "root",
    "executable": "/opt/conda/bin/python",
    "cpu_count": 2,
    "cpu_count_logical": 4,
    "cpu_freq": {
        "current": 2000.168,
        "min": 0.0,
        "max": 0.0
    },
    "cpu_freq_per_core": [
        {
            "current": 2000.168,
            "min": 0.0,
            "max": 0.0
        },
        {
            "current": 2000.168,
            "min": 0.0,
            "max": 0.0
        },
        {
            "current": 2000.168,
            "min": 0.0,
            "max": 0.0
        },
        {
            "current": 2000.168,
            "min": 0.0,
            "max": 0.0
        }
    ],
    "disk": {
        "/": {
            "total": 8062.387607574463,
            "used": 5597.589012145996
        }
    },
    "gpu": "Tesla P100-PCIE-16GB",
    "gpu_count": 1,
    "gpu_devices": [
        {
            "name": "Tesla P100-PCIE-16GB",
            "memory_total": 17179869184
        }
    ],
    "memory": {
        "total": 31.357559204101562
    }
}
